{
    "a2b64a4b-0a1d-e8a3-56d0-9e91da8b3a5f": {
        "paletteKey": "FlexLayoutCol",
        "commentid": null,
        "designerReference": [
            {
                "_key": "componentLabel",
                "_value": "Column",
                "_type": "kv",
                "_attrDef": "p",
                "_useAsLabel": true
            },
            {
                "_key": "style",
                "_value": "",
                "_type": "kv",
                "_attrDef": "p"
            },
            {
                "_key": "class",
                "_value": "",
                "_type": "dav",
                "_attrDef": "p"
            },
            {
                "_key": "fxFlex",
                "_value": "",
                "_type": "kv",
                "_attrDef": "p"
            },
            {
                "_key": "fxLayoutGap",
                "_value": "",
                "_type": "kv",
                "_attrDef": "p"
            },
            {
                "_key": "wrap",
                "_value": "wrap",
                "_type": "a",
                "_attrDef": "p"
            },
            {
                "_key": "layoutAlign",
                "_value": "start",
                "_type": "a",
                "_attrDef": "p"
            },
            {
                "_key": "pLayoutAlign",
                "_value": "stretch",
                "_type": "a",
                "_attrDef": "p"
            },
            {
                "_key": "[fxShow]",
                "_value": "true",
                "_type": "kv",
                "_attrDef": "p"
            }
        ],
        "b5a9c28d-d781-d665-bb58-95116241b8aa": {
            "paletteKey": "NG-icon",
            "parentEditorKey": "a2b64a4b-0a1d-e8a3-56d0-9e91da8b3a5f",
            "commentid": null,
            "designerReference": [
                {
                    "_key": "style",
                    "_value": "    position: absolute;     z-index: 16668; top: 15px;     right: 19px; ",
                    "_type": "kv",
                    "_attrDef": "p"
                },
                {
                    "_key": "class",
                    "_value": [
                        "right",
                        "color-b"
                    ],
                    "_type": "dav",
                    "_attrDef": "p"
                },
                {
                    "_key": "IconName",
                    "_value": "close",
                    "_type": "a",
                    "_attrDef": "p",
                    "_useAsLabel": true
                },
                {
                    "_key": "[inline]",
                    "_value": "",
                    "_type": "kv",
                    "_attrDef": "p"
                },
                {
                    "_key": "color",
                    "_value": "",
                    "_type": "kv",
                    "_attrDef": "p"
                },
                {
                    "_key": "(click)",
                    "_value": "showsidenav()",
                    "_type": "kv",
                    "_attrDef": "c",
                    "objValue": {
                        "nodeID": "sd_FKSyQSUP8DiZ3iht",
                        "functionName": "showsidenav",
                        "activeTree": "pages",
                        "z": "sd_fUkCGY1L0VBmLNIy",
                        "input": []
                    }
                }
            ]
        },
        "a6a1475d-80d0-26ef-ae9e-a11cfad9323e": {
            "paletteKey": "NEUTRINOS_VIEW_sidenav",
            "parentEditorKey": "a2b64a4b-0a1d-e8a3-56d0-9e91da8b3a5f",
            "commentid": null,
            "designerReference": [
                {
                    "_key": "componentLabel",
                    "_value": "sidenav",
                    "_type": "kv",
                    "_attrDef": "p",
                    "_useAsLabel": true
                },
                {
                    "_key": "style",
                    "_value": "position: absolute;     z-index: 16667;         background: #f5f5f5;      height: 100%;      left: 0;     right: 0;     top: 0;     bottom: 0;",
                    "_type": "kv",
                    "_attrDef": "p"
                },
                {
                    "_key": "class",
                    "_value": [
                        "right"
                    ],
                    "_type": "dav",
                    "_attrDef": "p"
                },
                {
                    "_key": "*ngIf",
                    "_value": "page.hidesidenav",
                    "_type": "kv",
                    "_attrDef": "c"
                }
            ]
        }
    },
    "dff60f77-5629-a0cc-89b8-ff82d1d35d13": {
        "paletteKey": "FlexLayoutCol",
        "commentid": null,
        "designerReference": [
            {
                "_key": "componentLabel",
                "_value": "Column",
                "_type": "kv",
                "_attrDef": "p",
                "_useAsLabel": true
            },
            {
                "_key": "style",
                "_value": "",
                "_type": "kv",
                "_attrDef": "p"
            },
            {
                "_key": "class",
                "_value": "",
                "_type": "dav",
                "_attrDef": "p"
            },
            {
                "_key": "fxFlex",
                "_value": "",
                "_type": "kv",
                "_attrDef": "p"
            },
            {
                "_key": "fxLayoutGap",
                "_value": "",
                "_type": "kv",
                "_attrDef": "p"
            },
            {
                "_key": "wrap",
                "_value": "wrap",
                "_type": "a",
                "_attrDef": "p"
            },
            {
                "_key": "layoutAlign",
                "_value": "start",
                "_type": "a",
                "_attrDef": "p"
            },
            {
                "_key": "pLayoutAlign",
                "_value": "center",
                "_type": "a",
                "_attrDef": "p"
            },
            {
                "_key": "[fxShow]",
                "_value": "true",
                "_type": "kv",
                "_attrDef": "p"
            }
        ],
        "55a23585-2b50-b2d9-e492-f507fdd320e1": {
            "paletteKey": "FlexLayoutCol",
            "parentEditorKey": "dff60f77-5629-a0cc-89b8-ff82d1d35d13",
            "commentid": null,
            "designerReference": [
                {
                    "_key": "componentLabel",
                    "_value": "Column",
                    "_type": "kv",
                    "_attrDef": "p",
                    "_useAsLabel": true
                },
                {
                    "_key": "style",
                    "_value": "",
                    "_type": "kv",
                    "_attrDef": "p"
                },
                {
                    "_key": "class",
                    "_value": [
                        "standard-width"
                    ],
                    "_type": "dav",
                    "_attrDef": "p"
                },
                {
                    "_key": "fxFlex",
                    "_value": "",
                    "_type": "kv",
                    "_attrDef": "p"
                },
                {
                    "_key": "fxLayoutGap",
                    "_value": "1em",
                    "_type": "kv",
                    "_attrDef": "p"
                },
                {
                    "_key": "wrap",
                    "_value": "wrap",
                    "_type": "a",
                    "_attrDef": "p"
                },
                {
                    "_key": "layoutAlign",
                    "_value": "start",
                    "_type": "a",
                    "_attrDef": "p"
                },
                {
                    "_key": "pLayoutAlign",
                    "_value": "stretch",
                    "_type": "a",
                    "_attrDef": "p"
                },
                {
                    "_key": "[fxShow]",
                    "_value": "true",
                    "_type": "kv",
                    "_attrDef": "p"
                }
            ],
            "302bcc0f-fe02-7bb9-64c8-13d2a0327773": {
                "paletteKey": "FlexLayoutRow",
                "parentEditorKey": "55a23585-2b50-b2d9-e492-f507fdd320e1",
                "commentid": null,
                "designerReference": [
                    {
                        "_key": "componentLabel",
                        "_value": "Row",
                        "_type": "kv",
                        "_attrDef": "p",
                        "_useAsLabel": true
                    },
                    {
                        "_key": "style",
                        "_value": "",
                        "_type": "kv",
                        "_attrDef": "p"
                    },
                    {
                        "_key": "class",
                        "_value": [
                            "fixed-width",
                            "fixed",
                            "z-index",
                            "padding-0px-15px",
                            "bg-blue",
                            "height-50px"
                        ],
                        "_type": "dav",
                        "_attrDef": "p"
                    },
                    {
                        "_key": "fxFlex",
                        "_value": "",
                        "_type": "kv",
                        "_attrDef": "p"
                    },
                    {
                        "_key": "fxLayoutGap",
                        "_value": "",
                        "_type": "kv",
                        "_attrDef": "p"
                    },
                    {
                        "_key": "wrap",
                        "_value": "wrap",
                        "_type": "a",
                        "_attrDef": "p"
                    },
                    {
                        "_key": "layoutAlign",
                        "_value": "start",
                        "_type": "a",
                        "_attrDef": "p"
                    },
                    {
                        "_key": "pLayoutAlign",
                        "_value": "center",
                        "_type": "a",
                        "_attrDef": "p"
                    },
                    {
                        "_key": "[fxShow]",
                        "_value": "true",
                        "_type": "kv",
                        "_attrDef": "p"
                    }
                ],
                "24c1bb59-4992-012b-7a83-549125d909b9": {
                    "paletteKey": "FlexLayoutCol",
                    "parentEditorKey": "302bcc0f-fe02-7bb9-64c8-13d2a0327773",
                    "commentid": null,
                    "designerReference": [
                        {
                            "_key": "componentLabel",
                            "_value": "Column",
                            "_type": "kv",
                            "_attrDef": "p",
                            "_useAsLabel": true
                        },
                        {
                            "_key": "style",
                            "_value": "",
                            "_type": "kv",
                            "_attrDef": "p"
                        },
                        {
                            "_key": "class",
                            "_value": [
                                "square-30px"
                            ],
                            "_type": "dav",
                            "_attrDef": "p"
                        },
                        {
                            "_key": "fxFlex",
                            "_value": "",
                            "_type": "kv",
                            "_attrDef": "p"
                        },
                        {
                            "_key": "fxLayoutGap",
                            "_value": "",
                            "_type": "kv",
                            "_attrDef": "p"
                        },
                        {
                            "_key": "wrap",
                            "_value": "wrap",
                            "_type": "a",
                            "_attrDef": "p"
                        },
                        {
                            "_key": "layoutAlign",
                            "_value": "start",
                            "_type": "a",
                            "_attrDef": "p"
                        },
                        {
                            "_key": "pLayoutAlign",
                            "_value": "stretch",
                            "_type": "a",
                            "_attrDef": "p"
                        },
                        {
                            "_key": "[fxShow]",
                            "_value": "true",
                            "_type": "kv",
                            "_attrDef": "p"
                        }
                    ],
                    "feedaa9f-f96d-472c-1d7e-8722eac32361": {
                        "paletteKey": "NG-image",
                        "parentEditorKey": "24c1bb59-4992-012b-7a83-549125d909b9",
                        "commentid": null,
                        "designerReference": [
                            {
                                "_key": "componentLabel",
                                "_value": "Image",
                                "_type": "kv",
                                "_attrDef": "p",
                                "_useAsLabel": true
                            },
                            {
                                "_key": "style",
                                "_value": "",
                                "_type": "kv",
                                "_attrDef": "p"
                            },
                            {
                                "_key": "class",
                                "_value": [
                                    "full-height",
                                    "full-width"
                                ],
                                "_type": "dav",
                                "_attrDef": "p"
                            },
                            {
                                "_key": "imgSrc",
                                "_value": "./Web/Images/account.png",
                                "_type": "kv",
                                "_attrDef": "p"
                            },
                            {
                                "_key": "alt",
                                "_value": "",
                                "_type": "kv",
                                "_attrDef": "p"
                            },
                            {
                                "_key": "[src]",
                                "_value": "",
                                "_type": "kv",
                                "_attrDef": "p"
                            },
                            {
                                "_key": "imgSecure",
                                "_value": "",
                                "_type": "a",
                                "_attrDef": "p"
                            },
                            {
                                "_key": "width",
                                "_value": "",
                                "_type": "kv",
                                "_attrDef": "p"
                            },
                            {
                                "_key": "srcset",
                                "_value": "",
                                "_type": "kv",
                                "_attrDef": "p"
                            },
                            {
                                "_key": "sizes",
                                "_value": "",
                                "_type": "kv",
                                "_attrDef": "p"
                            },
                            {
                                "_key": "(click)",
                                "_value": "showsidenav()",
                                "_type": "kv",
                                "_attrDef": "c",
                                "objValue": {
                                    "nodeID": "sd_FKSyQSUP8DiZ3iht",
                                    "functionName": "showsidenav",
                                    "activeTree": "pages",
                                    "z": "sd_fUkCGY1L0VBmLNIy",
                                    "input": []
                                }
                            }
                        ]
                    }
                },
                "1c73017d-cdd3-88b5-e0f0-675fb7a6dbb6": {
                    "paletteKey": "FlexLayoutCol",
                    "parentEditorKey": "302bcc0f-fe02-7bb9-64c8-13d2a0327773",
                    "commentid": null,
                    "designerReference": [
                        {
                            "_key": "componentLabel",
                            "_value": "Column",
                            "_type": "kv",
                            "_attrDef": "p",
                            "_useAsLabel": true
                        },
                        {
                            "_key": "style",
                            "_value": "",
                            "_type": "kv",
                            "_attrDef": "p"
                        },
                        {
                            "_key": "class",
                            "_value": "",
                            "_type": "dav",
                            "_attrDef": "p"
                        },
                        {
                            "_key": "fxFlex",
                            "_value": "90",
                            "_type": "kv",
                            "_attrDef": "p"
                        },
                        {
                            "_key": "fxLayoutGap",
                            "_value": "",
                            "_type": "kv",
                            "_attrDef": "p"
                        },
                        {
                            "_key": "wrap",
                            "_value": "wrap",
                            "_type": "a",
                            "_attrDef": "p"
                        },
                        {
                            "_key": "layoutAlign",
                            "_value": "start",
                            "_type": "a",
                            "_attrDef": "p"
                        },
                        {
                            "_key": "pLayoutAlign",
                            "_value": "center",
                            "_type": "a",
                            "_attrDef": "p"
                        },
                        {
                            "_key": "[fxShow]",
                            "_value": "true",
                            "_type": "kv",
                            "_attrDef": "p"
                        }
                    ],
                    "c9af027b-4569-eb22-76d9-9521b2a40919": {
                        "paletteKey": "Html5",
                        "parentEditorKey": "1c73017d-cdd3-88b5-e0f0-675fb7a6dbb6",
                        "isAdvancedComponent": true,
                        "commentid": null,
                        "designerReference": [
                            {
                                "_key": "style",
                                "_value": "",
                                "_type": "kv",
                                "_attrDef": "p"
                            },
                            {
                                "_key": "class",
                                "_value": [
                                    "no-margin",
                                    "color-w",
                                    "poppins"
                                ],
                                "_type": "dav",
                                "_attrDef": "p"
                            },
                            {
                                "_key": "htmlElement",
                                "_value": "h3",
                                "_type": "dav",
                                "_attrDef": "p",
                                "_useAsLabel": true
                            },
                            {
                                "_key": "tagType",
                                "_value": "h3",
                                "_type": "a",
                                "_attrDef": "p",
                                "_visibility": false
                            },
                            {
                                "_key": "name",
                                "_value": "",
                                "_type": "kv",
                                "_attrDef": "p",
                                "_visibility": false
                            },
                            {
                                "_key": "sandbox",
                                "_value": "",
                                "_type": "kv",
                                "_attrDef": "p",
                                "_visibility": false
                            },
                            {
                                "_key": "src",
                                "_value": "",
                                "_type": "kv",
                                "_attrDef": "p",
                                "_visibility": false
                            },
                            {
                                "_key": "srcdoc",
                                "_value": "",
                                "_type": "kv",
                                "_attrDef": "p",
                                "_visibility": false
                            },
                            {
                                "_key": "width",
                                "_value": "",
                                "_type": "kv",
                                "_attrDef": "p",
                                "_visibility": false
                            },
                            {
                                "_key": "[autoplay]",
                                "_value": "",
                                "_type": "kv",
                                "_attrDef": "p",
                                "_visibility": false
                            },
                            {
                                "_key": "[loop]",
                                "_value": "",
                                "_type": "kv",
                                "_attrDef": "p",
                                "_visibility": false
                            },
                            {
                                "_key": "data",
                                "_value": "",
                                "_type": "kv",
                                "_attrDef": "p",
                                "_visibility": false
                            },
                            {
                                "_key": "audioSource",
                                "_value": [],
                                "_type": "a",
                                "_attrDef": "p",
                                "_visibility": false
                            },
                            {
                                "_key": "videoSource",
                                "_value": [],
                                "_type": "a",
                                "_attrDef": "p",
                                "_visibility": false
                            },
                            {
                                "_key": "audioDatasource",
                                "_value": "",
                                "_type": "a",
                                "_attrDef": "p",
                                "_visibility": false
                            },
                            {
                                "_key": "audioSrc",
                                "_value": "",
                                "_type": "a",
                                "_attrDef": "p",
                                "_visibility": false
                            },
                            {
                                "_key": "audioType",
                                "_value": "",
                                "_type": "a",
                                "_attrDef": "p",
                                "_visibility": false
                            },
                            {
                                "_key": "videoDatasource",
                                "_value": "",
                                "_type": "a",
                                "_attrDef": "p",
                                "_visibility": false
                            },
                            {
                                "_key": "videoSrc",
                                "_value": "",
                                "_type": "a",
                                "_attrDef": "p",
                                "_visibility": false
                            },
                            {
                                "_key": "videoType",
                                "_value": "",
                                "_type": "a",
                                "_attrDef": "p",
                                "_visibility": false
                            },
                            {
                                "_key": "(audioplay)",
                                "_value": "",
                                "_type": "a",
                                "_attrDef": "p",
                                "_visibility": false
                            },
                            {
                                "_key": "(videoplay)",
                                "_value": "",
                                "_type": "a",
                                "_attrDef": "p",
                                "_visibility": false
                            },
                            {
                                "_key": "(audiopause)",
                                "_value": "",
                                "_type": "kv",
                                "_attrDef": "p",
                                "_visibility": false
                            },
                            {
                                "_key": "(videopause)",
                                "_value": "",
                                "_type": "kv",
                                "_attrDef": "p",
                                "_visibility": false
                            },
                            {
                                "_key": "(audioended)",
                                "_value": "",
                                "_type": "kv",
                                "_attrDef": "p",
                                "_visibility": false
                            },
                            {
                                "_key": "(videoended)",
                                "_value": "",
                                "_type": "kv",
                                "_attrDef": "p",
                                "_visibility": false
                            }
                        ],
                        "47ddbc49-3942-c616-1fe2-79b6c9101888": {
                            "paletteKey": "html-editor",
                            "parentEditorKey": "c9af027b-4569-eb22-76d9-9521b2a40919",
                            "isAdvancedChildComponent": true,
                            "commentid": null,
                            "designerReference": [
                                {
                                    "_key": "style",
                                    "_value": "",
                                    "_type": "kv",
                                    "_attrDef": "p"
                                },
                                {
                                    "_key": "class",
                                    "_value": "",
                                    "_type": "dav",
                                    "_attrDef": "p"
                                },
                                {
                                    "_key": "html",
                                    "_value": "GlobalOne",
                                    "_type": "a",
                                    "_attrDef": "p"
                                }
                            ]
                        }
                    }
                }
            },
            "ee875a1a-0a81-f162-6e15-65d4da5bc826": {
                "paletteKey": "FlexLayoutCol",
                "parentEditorKey": "55a23585-2b50-b2d9-e492-f507fdd320e1",
                "commentid": null,
                "designerReference": [
                    {
                        "_key": "componentLabel",
                        "_value": "Column",
                        "_type": "kv",
                        "_attrDef": "p",
                        "_useAsLabel": true
                    },
                    {
                        "_key": "style",
                        "_value": "",
                        "_type": "kv",
                        "_attrDef": "p"
                    },
                    {
                        "_key": "class",
                        "_value": [
                            "margin-t-50px",
                            "padding-0px-15px"
                        ],
                        "_type": "dav",
                        "_attrDef": "p"
                    },
                    {
                        "_key": "fxFlex",
                        "_value": "",
                        "_type": "kv",
                        "_attrDef": "p"
                    },
                    {
                        "_key": "fxLayoutGap",
                        "_value": "",
                        "_type": "kv",
                        "_attrDef": "p"
                    },
                    {
                        "_key": "wrap",
                        "_value": "wrap",
                        "_type": "a",
                        "_attrDef": "p"
                    },
                    {
                        "_key": "layoutAlign",
                        "_value": "start",
                        "_type": "a",
                        "_attrDef": "p"
                    },
                    {
                        "_key": "pLayoutAlign",
                        "_value": "stretch",
                        "_type": "a",
                        "_attrDef": "p"
                    },
                    {
                        "_key": "[fxShow]",
                        "_value": "true",
                        "_type": "kv",
                        "_attrDef": "p"
                    }
                ],
                "a2c3e996-b757-23f3-40c6-a6e362d0d622": {
                    "paletteKey": "NEUTRINOS_VIEW_long_card",
                    "parentEditorKey": "ee875a1a-0a81-f162-6e15-65d4da5bc826",
                    "commentid": null,
                    "designerReference": [
                        {
                            "_key": "componentLabel",
                            "_value": "long_card",
                            "_type": "kv",
                            "_attrDef": "p",
                            "_useAsLabel": true
                        },
                        {
                            "_key": "style",
                            "_value": "",
                            "_type": "kv",
                            "_attrDef": "p"
                        },
                        {
                            "_key": "class",
                            "_value": "",
                            "_type": "dav",
                            "_attrDef": "p"
                        }
                    ]
                }
            },
            "1f6ca927-bfff-526b-e3a4-cb35cff148d5": {
                "paletteKey": "FlexLayoutCol",
                "parentEditorKey": "55a23585-2b50-b2d9-e492-f507fdd320e1",
                "commentid": null,
                "designerReference": [
                    {
                        "_key": "componentLabel",
                        "_value": "Column",
                        "_type": "kv",
                        "_attrDef": "p",
                        "_useAsLabel": true
                    },
                    {
                        "_key": "style",
                        "_value": "",
                        "_type": "kv",
                        "_attrDef": "p"
                    },
                    {
                        "_key": "class",
                        "_value": [
                            "padding-0px-15px"
                        ],
                        "_type": "dav",
                        "_attrDef": "p"
                    },
                    {
                        "_key": "fxFlex",
                        "_value": "",
                        "_type": "kv",
                        "_attrDef": "p"
                    },
                    {
                        "_key": "fxLayoutGap",
                        "_value": "",
                        "_type": "kv",
                        "_attrDef": "p"
                    },
                    {
                        "_key": "wrap",
                        "_value": "wrap",
                        "_type": "a",
                        "_attrDef": "p"
                    },
                    {
                        "_key": "layoutAlign",
                        "_value": "start",
                        "_type": "a",
                        "_attrDef": "p"
                    },
                    {
                        "_key": "pLayoutAlign",
                        "_value": "stretch",
                        "_type": "a",
                        "_attrDef": "p"
                    },
                    {
                        "_key": "[fxShow]",
                        "_value": "true",
                        "_type": "kv",
                        "_attrDef": "p"
                    }
                ],
                "8b441b10-0f1e-5964-87b7-465a07c59ef8": {
                    "paletteKey": "FlexLayoutRow",
                    "parentEditorKey": "1f6ca927-bfff-526b-e3a4-cb35cff148d5",
                    "commentid": null,
                    "designerReference": [
                        {
                            "_key": "componentLabel",
                            "_value": "Row",
                            "_type": "kv",
                            "_attrDef": "p",
                            "_useAsLabel": true
                        },
                        {
                            "_key": "style",
                            "_value": "",
                            "_type": "kv",
                            "_attrDef": "p"
                        },
                        {
                            "_key": "class",
                            "_value": [
                                "poppins"
                            ],
                            "_type": "dav",
                            "_attrDef": "p"
                        },
                        {
                            "_key": "fxFlex",
                            "_value": "",
                            "_type": "kv",
                            "_attrDef": "p"
                        },
                        {
                            "_key": "fxLayoutGap",
                            "_value": "",
                            "_type": "kv",
                            "_attrDef": "p"
                        },
                        {
                            "_key": "wrap",
                            "_value": "wrap",
                            "_type": "a",
                            "_attrDef": "p"
                        },
                        {
                            "_key": "layoutAlign",
                            "_value": "space-between",
                            "_type": "a",
                            "_attrDef": "p"
                        },
                        {
                            "_key": "pLayoutAlign",
                            "_value": "center",
                            "_type": "a",
                            "_attrDef": "p"
                        },
                        {
                            "_key": "[fxShow]",
                            "_value": "true",
                            "_type": "kv",
                            "_attrDef": "p"
                        }
                    ],
                    "93d862ad-7e21-a0a9-bdbd-72e229efd7c7": {
                        "paletteKey": "FlexLayoutCol",
                        "parentEditorKey": "8b441b10-0f1e-5964-87b7-465a07c59ef8",
                        "commentid": null,
                        "designerReference": [
                            {
                                "_key": "componentLabel",
                                "_value": "Column",
                                "_type": "kv",
                                "_attrDef": "p",
                                "_useAsLabel": true
                            },
                            {
                                "_key": "style",
                                "_value": "",
                                "_type": "kv",
                                "_attrDef": "p"
                            },
                            {
                                "_key": "class",
                                "_value": "",
                                "_type": "dav",
                                "_attrDef": "p"
                            },
                            {
                                "_key": "fxFlex",
                                "_value": "",
                                "_type": "kv",
                                "_attrDef": "p"
                            },
                            {
                                "_key": "fxLayoutGap",
                                "_value": "",
                                "_type": "kv",
                                "_attrDef": "p"
                            },
                            {
                                "_key": "wrap",
                                "_value": "wrap",
                                "_type": "a",
                                "_attrDef": "p"
                            },
                            {
                                "_key": "layoutAlign",
                                "_value": "start",
                                "_type": "a",
                                "_attrDef": "p"
                            },
                            {
                                "_key": "pLayoutAlign",
                                "_value": "stretch",
                                "_type": "a",
                                "_attrDef": "p"
                            },
                            {
                                "_key": "[fxShow]",
                                "_value": "true",
                                "_type": "kv",
                                "_attrDef": "p"
                            }
                        ],
                        "00a6768b-88f7-879c-46c5-d0d6f13bb799": {
                            "paletteKey": "Html5",
                            "parentEditorKey": "93d862ad-7e21-a0a9-bdbd-72e229efd7c7",
                            "isAdvancedComponent": true,
                            "commentid": null,
                            "designerReference": [
                                {
                                    "_key": "style",
                                    "_value": "",
                                    "_type": "kv",
                                    "_attrDef": "p"
                                },
                                {
                                    "_key": "class",
                                    "_value": [
                                        "no-margin"
                                    ],
                                    "_type": "dav",
                                    "_attrDef": "p"
                                },
                                {
                                    "_key": "htmlElement",
                                    "_value": "h4",
                                    "_type": "dav",
                                    "_attrDef": "p",
                                    "_useAsLabel": true
                                },
                                {
                                    "_key": "tagType",
                                    "_value": "h4",
                                    "_type": "a",
                                    "_attrDef": "p",
                                    "_visibility": false
                                },
                                {
                                    "_key": "name",
                                    "_value": "",
                                    "_type": "kv",
                                    "_attrDef": "p",
                                    "_visibility": false
                                },
                                {
                                    "_key": "sandbox",
                                    "_value": "",
                                    "_type": "kv",
                                    "_attrDef": "p",
                                    "_visibility": false
                                },
                                {
                                    "_key": "src",
                                    "_value": "",
                                    "_type": "kv",
                                    "_attrDef": "p",
                                    "_visibility": false
                                },
                                {
                                    "_key": "srcdoc",
                                    "_value": "",
                                    "_type": "kv",
                                    "_attrDef": "p",
                                    "_visibility": false
                                },
                                {
                                    "_key": "width",
                                    "_value": "",
                                    "_type": "kv",
                                    "_attrDef": "p",
                                    "_visibility": false
                                },
                                {
                                    "_key": "[autoplay]",
                                    "_value": "",
                                    "_type": "kv",
                                    "_attrDef": "p",
                                    "_visibility": false
                                },
                                {
                                    "_key": "[loop]",
                                    "_value": "",
                                    "_type": "kv",
                                    "_attrDef": "p",
                                    "_visibility": false
                                },
                                {
                                    "_key": "data",
                                    "_value": "",
                                    "_type": "kv",
                                    "_attrDef": "p",
                                    "_visibility": false
                                },
                                {
                                    "_key": "audioSource",
                                    "_value": [],
                                    "_type": "a",
                                    "_attrDef": "p",
                                    "_visibility": false
                                },
                                {
                                    "_key": "videoSource",
                                    "_value": [],
                                    "_type": "a",
                                    "_attrDef": "p",
                                    "_visibility": false
                                },
                                {
                                    "_key": "audioDatasource",
                                    "_value": "",
                                    "_type": "a",
                                    "_attrDef": "p",
                                    "_visibility": false
                                },
                                {
                                    "_key": "audioSrc",
                                    "_value": "",
                                    "_type": "a",
                                    "_attrDef": "p",
                                    "_visibility": false
                                },
                                {
                                    "_key": "audioType",
                                    "_value": "",
                                    "_type": "a",
                                    "_attrDef": "p",
                                    "_visibility": false
                                },
                                {
                                    "_key": "videoDatasource",
                                    "_value": "",
                                    "_type": "a",
                                    "_attrDef": "p",
                                    "_visibility": false
                                },
                                {
                                    "_key": "videoSrc",
                                    "_value": "",
                                    "_type": "a",
                                    "_attrDef": "p",
                                    "_visibility": false
                                },
                                {
                                    "_key": "videoType",
                                    "_value": "",
                                    "_type": "a",
                                    "_attrDef": "p",
                                    "_visibility": false
                                },
                                {
                                    "_key": "(audioplay)",
                                    "_value": "",
                                    "_type": "a",
                                    "_attrDef": "p",
                                    "_visibility": false
                                },
                                {
                                    "_key": "(videoplay)",
                                    "_value": "",
                                    "_type": "a",
                                    "_attrDef": "p",
                                    "_visibility": false
                                },
                                {
                                    "_key": "(audiopause)",
                                    "_value": "",
                                    "_type": "kv",
                                    "_attrDef": "p",
                                    "_visibility": false
                                },
                                {
                                    "_key": "(videopause)",
                                    "_value": "",
                                    "_type": "kv",
                                    "_attrDef": "p",
                                    "_visibility": false
                                },
                                {
                                    "_key": "(audioended)",
                                    "_value": "",
                                    "_type": "kv",
                                    "_attrDef": "p",
                                    "_visibility": false
                                },
                                {
                                    "_key": "(videoended)",
                                    "_value": "",
                                    "_type": "kv",
                                    "_attrDef": "p",
                                    "_visibility": false
                                }
                            ],
                            "7feccb07-8ea3-aa5f-1bdb-6d5247b0ce05": {
                                "paletteKey": "html-editor",
                                "parentEditorKey": "00a6768b-88f7-879c-46c5-d0d6f13bb799",
                                "isAdvancedChildComponent": true,
                                "commentid": null,
                                "designerReference": [
                                    {
                                        "_key": "style",
                                        "_value": "",
                                        "_type": "kv",
                                        "_attrDef": "p"
                                    },
                                    {
                                        "_key": "class",
                                        "_value": "",
                                        "_type": "dav",
                                        "_attrDef": "p"
                                    },
                                    {
                                        "_key": "html",
                                        "_value": "Favorites",
                                        "_type": "a",
                                        "_attrDef": "p"
                                    }
                                ]
                            }
                        }
                    },
                    "64c1fd7f-e766-aaa3-9bef-e5d3d86e248d": {
                        "paletteKey": "FlexLayoutRow",
                        "parentEditorKey": "8b441b10-0f1e-5964-87b7-465a07c59ef8",
                        "commentid": null,
                        "designerReference": [
                            {
                                "_key": "componentLabel",
                                "_value": "Row",
                                "_type": "kv",
                                "_attrDef": "p",
                                "_useAsLabel": true
                            },
                            {
                                "_key": "style",
                                "_value": "",
                                "_type": "kv",
                                "_attrDef": "p"
                            },
                            {
                                "_key": "class",
                                "_value": [
                                    "padding-right-10px"
                                ],
                                "_type": "dav",
                                "_attrDef": "p"
                            },
                            {
                                "_key": "fxFlex",
                                "_value": "",
                                "_type": "kv",
                                "_attrDef": "p"
                            },
                            {
                                "_key": "fxLayoutGap",
                                "_value": "",
                                "_type": "kv",
                                "_attrDef": "p"
                            },
                            {
                                "_key": "wrap",
                                "_value": "wrap",
                                "_type": "a",
                                "_attrDef": "p"
                            },
                            {
                                "_key": "layoutAlign",
                                "_value": "start",
                                "_type": "a",
                                "_attrDef": "p"
                            },
                            {
                                "_key": "pLayoutAlign",
                                "_value": "stretch",
                                "_type": "a",
                                "_attrDef": "p"
                            },
                            {
                                "_key": "[fxShow]",
                                "_value": "true",
                                "_type": "kv",
                                "_attrDef": "p"
                            }
                        ],
                        "1afcbbd2-b203-f385-8ca5-06ae52c22696": {
                            "paletteKey": "Html5",
                            "parentEditorKey": "64c1fd7f-e766-aaa3-9bef-e5d3d86e248d",
                            "isAdvancedComponent": true,
                            "commentid": null,
                            "designerReference": [
                                {
                                    "_key": "style",
                                    "_value": "font-weight: 600",
                                    "_type": "kv",
                                    "_attrDef": "p"
                                },
                                {
                                    "_key": "class",
                                    "_value": [
                                        "pointer",
                                        "color-b"
                                    ],
                                    "_type": "dav",
                                    "_attrDef": "p"
                                },
                                {
                                    "_key": "htmlElement",
                                    "_value": "div",
                                    "_type": "dav",
                                    "_attrDef": "p",
                                    "_useAsLabel": true
                                },
                                {
                                    "_key": "tagType",
                                    "_value": "",
                                    "_type": "a",
                                    "_attrDef": "p",
                                    "_visibility": false
                                },
                                {
                                    "_key": "name",
                                    "_value": "",
                                    "_type": "kv",
                                    "_attrDef": "p",
                                    "_visibility": false
                                },
                                {
                                    "_key": "sandbox",
                                    "_value": "",
                                    "_type": "kv",
                                    "_attrDef": "p",
                                    "_visibility": false
                                },
                                {
                                    "_key": "src",
                                    "_value": "",
                                    "_type": "kv",
                                    "_attrDef": "p",
                                    "_visibility": false
                                },
                                {
                                    "_key": "srcdoc",
                                    "_value": "",
                                    "_type": "kv",
                                    "_attrDef": "p",
                                    "_visibility": false
                                },
                                {
                                    "_key": "width",
                                    "_value": "",
                                    "_type": "kv",
                                    "_attrDef": "p",
                                    "_visibility": false
                                },
                                {
                                    "_key": "[autoplay]",
                                    "_value": "",
                                    "_type": "kv",
                                    "_attrDef": "p",
                                    "_visibility": false
                                },
                                {
                                    "_key": "[loop]",
                                    "_value": "",
                                    "_type": "kv",
                                    "_attrDef": "p",
                                    "_visibility": false
                                },
                                {
                                    "_key": "data",
                                    "_value": "",
                                    "_type": "kv",
                                    "_attrDef": "p",
                                    "_visibility": false
                                },
                                {
                                    "_key": "audioSource",
                                    "_value": [],
                                    "_type": "a",
                                    "_attrDef": "p",
                                    "_visibility": false
                                },
                                {
                                    "_key": "videoSource",
                                    "_value": [],
                                    "_type": "a",
                                    "_attrDef": "p",
                                    "_visibility": false
                                },
                                {
                                    "_key": "audioDatasource",
                                    "_value": "",
                                    "_type": "a",
                                    "_attrDef": "p",
                                    "_visibility": false
                                },
                                {
                                    "_key": "audioSrc",
                                    "_value": "",
                                    "_type": "a",
                                    "_attrDef": "p",
                                    "_visibility": false
                                },
                                {
                                    "_key": "audioType",
                                    "_value": "",
                                    "_type": "a",
                                    "_attrDef": "p",
                                    "_visibility": false
                                },
                                {
                                    "_key": "videoDatasource",
                                    "_value": "",
                                    "_type": "a",
                                    "_attrDef": "p",
                                    "_visibility": false
                                },
                                {
                                    "_key": "videoSrc",
                                    "_value": "",
                                    "_type": "a",
                                    "_attrDef": "p",
                                    "_visibility": false
                                },
                                {
                                    "_key": "videoType",
                                    "_value": "",
                                    "_type": "a",
                                    "_attrDef": "p",
                                    "_visibility": false
                                },
                                {
                                    "_key": "(audioplay)",
                                    "_value": "",
                                    "_type": "a",
                                    "_attrDef": "p",
                                    "_visibility": false
                                },
                                {
                                    "_key": "(videoplay)",
                                    "_value": "",
                                    "_type": "a",
                                    "_attrDef": "p",
                                    "_visibility": false
                                },
                                {
                                    "_key": "(audiopause)",
                                    "_value": "",
                                    "_type": "kv",
                                    "_attrDef": "p",
                                    "_visibility": false
                                },
                                {
                                    "_key": "(videopause)",
                                    "_value": "",
                                    "_type": "kv",
                                    "_attrDef": "p",
                                    "_visibility": false
                                },
                                {
                                    "_key": "(audioended)",
                                    "_value": "",
                                    "_type": "kv",
                                    "_attrDef": "p",
                                    "_visibility": false
                                },
                                {
                                    "_key": "(videoended)",
                                    "_value": "",
                                    "_type": "kv",
                                    "_attrDef": "p",
                                    "_visibility": false
                                },
                                {
                                    "_key": "routerLink",
                                    "_value": "/logged_in_landing/favourites",
                                    "_type": "kv",
                                    "_attrDef": "c"
                                }
                            ],
                            "92619a92-cde7-053d-32bf-94bf7e801c4e": {
                                "paletteKey": "html-editor",
                                "parentEditorKey": "1afcbbd2-b203-f385-8ca5-06ae52c22696",
                                "isAdvancedChildComponent": true,
                                "commentid": null,
                                "designerReference": [
                                    {
                                        "_key": "style",
                                        "_value": "",
                                        "_type": "kv",
                                        "_attrDef": "p"
                                    },
                                    {
                                        "_key": "class",
                                        "_value": "",
                                        "_type": "dav",
                                        "_attrDef": "p"
                                    },
                                    {
                                        "_key": "html",
                                        "_value": "Edit",
                                        "_type": "a",
                                        "_attrDef": "p"
                                    }
                                ]
                            }
                        },
                        "a0a263e7-b3f3-0f7e-8546-82b3ec6c2ddf": {
                            "paletteKey": "NG-icon",
                            "parentEditorKey": "64c1fd7f-e766-aaa3-9bef-e5d3d86e248d",
                            "commentid": null,
                            "designerReference": [
                                {
                                    "_key": "style",
                                    "_value": "",
                                    "_type": "kv",
                                    "_attrDef": "p"
                                },
                                {
                                    "_key": "class",
                                    "_value": [
                                        "color-b"
                                    ],
                                    "_type": "dav",
                                    "_attrDef": "p"
                                },
                                {
                                    "_key": "IconName",
                                    "_value": "chevron_right",
                                    "_type": "a",
                                    "_attrDef": "p",
                                    "_useAsLabel": true
                                },
                                {
                                    "_key": "[inline]",
                                    "_value": "",
                                    "_type": "kv",
                                    "_attrDef": "p"
                                },
                                {
                                    "_key": "color",
                                    "_value": "",
                                    "_type": "kv",
                                    "_attrDef": "p"
                                }
                            ]
                        }
                    }
                },
                "ac2d12ad-3186-c3a6-9294-77f650dee77f": {
                    "paletteKey": "NEUTRINOS_VIEW_medium_card",
                    "parentEditorKey": "1f6ca927-bfff-526b-e3a4-cb35cff148d5",
                    "commentid": null,
                    "designerReference": [
                        {
                            "_key": "componentLabel",
                            "_value": "medium_card",
                            "_type": "kv",
                            "_attrDef": "p",
                            "_useAsLabel": true
                        },
                        {
                            "_key": "style",
                            "_value": "",
                            "_type": "kv",
                            "_attrDef": "p"
                        },
                        {
                            "_key": "class",
                            "_value": "",
                            "_type": "dav",
                            "_attrDef": "p"
                        }
                    ]
                }
            }
        }
    }
}
